{"ops_by_id": {"b2f63c2c-9c5f-43f1-9e92-49f7d9f19a41": {"status": "cancelled", "operation_type": "patient", "payload": null, "status_code": 409, "error_code": "MOCK_CANCELLED", "error_detail": "Mock operation was cancelled by user.", "schema": {"$defs": {"AddressDto": {"properties": {"country": {"anyOf": [{"type": "string"}, {"type": "null"}], "default": null, "title": "Country"}, "city": {"anyOf": [{"type": "string"}, {"type": "null"}], "default": null, "title": "City"}, "state": {"anyOf": [{"type": "string"}, {"type": "null"}], "default": null, "title": "State"}, "postalCode": {"anyOf": [{"type": "string"}, {"type": "null"}], "default": null, "title": "Postalcode"}, "street": {"anyOf": [{"type": "string"}, {"type": "null"}], "default": null, "title": "Street"}, "addressSupplement": {"anyOf": [{"type": "string"}, {"type": "null"}], "default": null, "title": "Addresssupplement"}}, "title": "AddressDto", "type": "object"}, "CommunicationDto": {"properties": {"communicationType": {"title": "Communicationtype", "type": "string", "enum": ["PHONE", "EMAIL", "FAX", "PAGER", "URL", "SMS"]}, "use": {"title": "Use", "type": "string", "enum": ["WORK", "PRIVATE", "HOME", "TEMP", "OLD", "HOLIDAY", "MOBILE", "OTHER"]}, "value": {"title": "Value", "type": "string"}}, "required": ["communicationType", "use", "value"], "title": "CommunicationDto", "type": "object"}}, "properties": {"id": {"title": "Id", "type": "string"}, "resourceType": {"default": "Patient", "title": "Resourcetype", "type": "string"}, "resourceName": {"title": "Resourcename", "type": "string"}, "ehrId": {"title": "Ehrid", "type": "string"}, "ahvNumber": {"anyOf": [{"type": "string"}, {"type": "null"}], "default": null, "title": "Ahvnumber"}, "gender": {"anyOf": [{"type": "string"}, {"type": "null"}], "default": null, "title": "Gender", "enum": ["male", "female", "diverse", "other", "unknown"]}, "name": {"anyOf": [{"type": "string"}, {"type": "null"}], "default": null, "title": "Name"}, "surname": {"anyOf": [{"type": "string"}, {"type": "null"}], "default": null, "title": "Surname"}, "birthdate": {"anyOf": [{"type": "string"}, {"type": "null"}], "default": null, "title": "Birthdate"}, "deceased": {"anyOf": [{"type": "boolean"}, {"type": "null"}], "default": null, "title": "Deceased"}, "addresses": {"items": {"$ref": "#/$defs/AddressDto"}, "title": "Addresses", "type": "array"}, "communications": {"items": {"$ref": "#/$defs/CommunicationDto"}, "title": "Communications", "type": "array"}}, "required": ["id", "resourceName", "ehrId"], "title": "PatientDto", "type": "object"}, "sample_payload": {"id": "7411", "resourceType": "Patient", "resourceName": "Patient", "ehrId": "123456", "communications": [], "addresses": []}, "form_url": "http://localhost:8000/api/interfaces/patients/mock/operations/b2f63c2c-9c5f-43f1-9e92-49f7d9f19a41/form", "created_at": "2026-03-17T10:15:47.412563+00:00", "updated_at": "2026-03-17T10:15:53.764172+00:00"}, "0378e267-8e2a-439a-b7af-649a35a5e710": {"status": "ready", "operation_type": "patient", "payload": {"id": "4711343", "resourceType": "Patient", "resourceName": "Patient", "ehrId": "123456", "communications": [{"communicationType": "PHONE", "use": "HOME", "value": "47623467523"}], "addresses": [], "ahvNumber": null, "gender": null, "name": "Test", "surname": "Toaster", "birthdate": "01.01.1967", "deceased": null}, "status_code": null, "error_code": null, "error_detail": null, "schema": {"$defs": {"AddressDto": {"properties": {"country": {"anyOf": [{"type": "string"}, {"type": "null"}], "default": null, "title": "Country"}, "city": {"anyOf": [{"type": "string"}, {"type": "null"}], "default": null, "title": "City"}, "state": {"anyOf": [{"type": "string"}, {"type": "null"}], "default": null, "title": "State"}, "postalCode": {"anyOf": [{"type": "string"}, {"type": "null"}], "default": null, "title": "Postalcode"}, "street": {"anyOf": [{"type": "string"}, {"type": "null"}], "default": null, "title": "Street"}, "addressSupplement": {"anyOf": [{"type": "string"}, {"type": "null"}], "default": null, "title": "Addresssupplement"}}, "title": "AddressDto", "type": "object"}, "CommunicationDto": {"properties": {"communicationType": {"title": "Communicationtype", "type": "string", "enum": ["PHONE", "EMAIL", "FAX", "PAGER", "URL", "SMS"]}, "use": {"title": "Use", "type": "string", "enum": ["WORK", "PRIVATE", "HOME", "TEMP", "OLD", "HOLIDAY", "MOBILE", "OTHER"]}, "value": {"title": "Value", "type": "string"}}, "required": ["communicationType", "use", "value"], "title": "CommunicationDto", "type": "object"}}, "properties": {"id": {"title": "Id", "type": "string"}, "resourceType": {"default": "Patient", "title": "Resourcetype", "type": "string"}, "resourceName": {"title": "Resourcename", "type": "string"}, "ehrId": {"title": "Ehrid", "type": "string"}, "ahvNumber": {"anyOf": [{"type": "string"}, {"type": "null"}], "default": null, "title": "Ahvnumber"}, "gender": {"anyOf": [{"type": "string"}, {"type": "null"}], "default": null, "title": "Gender", "enum": ["male", "female", "diverse", "other", "unknown"]}, "name": {"anyOf": [{"type": "string"}, {"type": "null"}], "default": null, "title": "Name"}, "surname": {"anyOf": [{"type": "string"}, {"type": "null"}], "default": null, "title": "Surname"}, "birthdate": {"anyOf": [{"type": "string"}, {"type": "null"}], "default": null, "title": "Birthdate"}, "deceased": {"anyOf": [{"type": "boolean"}, {"type": "null"}], "default": null, "title": "Deceased"}, "addresses": {"items": {"$ref": "#/$defs/AddressDto"}, "title": "Addresses", "type": "array"}, "communications": {"items": {"$ref": "#/$defs/CommunicationDto"}, "title": "Communications", "type": "array"}}, "required": ["id", "resourceName", "ehrId"], "title": "PatientDto", "type": "object"}, "sample_payload": {"id": "4711343", "resourceType": "Patient", "resourceName": "Patient", "ehrId": "123456", "communications": [], "addresses": []}, "form_url": "http://localhost:8000/api/interfaces/patients/mock/operations/0378e267-8e2a-439a-b7af-649a35a5e710/form", "created_at": "2026-03-17T10:16:06.287416+00:00", "updated_at": "2026-03-17T10:16:48.616521+00:00"}, "2a43da0b-c513-406f-a616-da7c9850c297": {"status": "ready", "operation_type": "patient", "payload": {"id": "545345346246", "resourceType": "Patient", "resourceName": "Patient", "ehrId": "123456", "communications": [{"communicationType": "EMAIL", "use": "HOME", "value": "424242"}], "addresses": [], "ahvNumber": null, "gender": "male", "name": "Hans", "surname": "M\u00fcller", "birthdate": "01.01.1970", "deceased": null}, "status_code": null, "error_code": null, "error_detail": null, "schema": {"$defs": {"AddressDto": {"properties": {"country": {"anyOf": [{"type": "string"}, {"type": "null"}], "default": null, "title": "Country"}, "city": {"anyOf": [{"type": "string"}, {"type": "null"}], "default": null, "title": "City"}, "state": {"anyOf": [{"type": "string"}, {"type": "null"}], "default": null, "title": "State"}, "postalCode": {"anyOf": [{"type": "string"}, {"type": "null"}], "default": null, "title": "Postalcode"}, "street": {"anyOf": [{"type": "string"}, {"type": "null"}], "default": null, "title": "Street"}, "addressSupplement": {"anyOf": [{"type": "string"}, {"type": "null"}], "default": null, "title": "Addresssupplement"}}, "title": "AddressDto", "type": "object"}, "CommunicationDto": {"properties": {"communicationType": {"title": "Communicationtype", "type": "string", "enum": ["PHONE", "EMAIL", "FAX", "PAGER", "URL", "SMS"]}, "use": {"title": "Use", "type": "string", "enum": ["WORK", "PRIVATE", "HOME", "TEMP", "OLD", "HOLIDAY", "MOBILE", "OTHER"]}, "value": {"title": "Value", "type": "string"}}, "required": ["communicationType", "use", "value"], "title": "CommunicationDto", "type": "object"}}, "properties": {"id": {"title": "Id", "type": "string"}, "resourceType": {"default": "Patient", "title": "Resourcetype", "type": "string"}, "resourceName": {"title": "Resourcename", "type": "string"}, "ehrId": {"title": "Ehrid", "type": "string"}, "ahvNumber": {"anyOf": [{"type": "string"}, {"type": "null"}], "default": null, "title": "Ahvnumber"}, "gender": {"anyOf": [{"type": "string"}, {"type": "null"}], "default": null, "title": "Gender", "enum": ["male", "female", "diverse", "other", "unknown"]}, "name": {"anyOf": [{"type": "string"}, {"type": "null"}], "default": null, "title": "Name"}, "surname": {"anyOf": [{"type": "string"}, {"type": "null"}], "default": null, "title": "Surname"}, "birthdate": {"anyOf": [{"type": "string"}, {"type": "null"}], "default": null, "title": "Birthdate"}, "deceased": {"anyOf": [{"type": "boolean"}, {"type": "null"}], "default": null, "title": "Deceased"}, "addresses": {"items": {"$ref": "#/$defs/AddressDto"}, "title": "Addresses", "type": "array"}, "communications": {"items": {"$ref": "#/$defs/CommunicationDto"}, "title": "Communications", "type": "array"}}, "required": ["id", "resourceName", "ehrId"], "title": "PatientDto", "type": "object"}, "sample_payload": {"id": "545345346246", "resourceType": "Patient", "resourceName": "Patient", "ehrId": "123456", "communications": [], "addresses": []}, "form_url": "http://localhost:8000/api/interfaces/patients/mock/operations/2a43da0b-c513-406f-a616-da7c9850c297/form", "created_at": "2026-03-18T09:59:02.563775+00:00", "updated_at": "2026-03-18T10:00:46.709513+00:00"}, "f77d6132-4300-44a5-a44b-c62255181ba5": {"status": "ready", "operation_type": "patient", "payload": {"id": "232244334", "resourceType": "Patient", "resourceName": "Patient", "ehrId": "123456", "communications": [{"communicationType": "PHONE", "use": "HOME", "value": "2353"}], "addresses": [], "ahvNumber": null, "gender": "male", "name": "Test", "surname": "Toaster", "birthdate": "01.01.1970", "deceased": null}, "status_code": null, "error_code": null, "error_detail": null, "schema": {"$defs": {"AddressDto": {"properties": {"country": {"anyOf": [{"type": "string"}, {"type": "null"}], "default": null, "title": "Country"}, "city": {"anyOf": [{"type": "string"}, {"type": "null"}], "default": null, "title": "City"}, "state": {"anyOf": [{"type": "string"}, {"type": "null"}], "default": null, "title": "State"}, "postalCode": {"anyOf": [{"type": "string"}, {"type": "null"}], "default": null, "title": "Postalcode"}, "street": {"anyOf": [{"type": "string"}, {"type": "null"}], "default": null, "title": "Street"}, "addressSupplement": {"anyOf": [{"type": "string"}, {"type": "null"}], "default": null, "title": "Addresssupplement"}}, "title": "AddressDto", "type": "object"}, "CommunicationDto": {"properties": {"communicationType": {"title": "Communicationtype", "type": "string", "enum": ["PHONE", "EMAIL", "FAX", "PAGER", "URL", "SMS"]}, "use": {"title": "Use", "type": "string", "enum": ["WORK", "PRIVATE", "HOME", "TEMP", "OLD", "HOLIDAY", "MOBILE", "OTHER"]}, "value": {"title": "Value", "type": "string"}}, "required": ["communicationType", "use", "value"], "title": "CommunicationDto", "type": "object"}}, "properties": {"id": {"title": "Id", "type": "string"}, "resourceType": {"default": "Patient", "title": "Resourcetype", "type": "string"}, "resourceName": {"title": "Resourcename", "type": "string"}, "ehrId": {"title": "Ehrid", "type": "string"}, "ahvNumber": {"anyOf": [{"type": "string"}, {"type": "null"}], "default": null, "title": "Ahvnumber"}, "gender": {"anyOf": [{"type": "string"}, {"type": "null"}], "default": null, "title": "Gender", "enum": ["male", "female", "diverse", "other", "unknown"]}, "name": {"anyOf": [{"type": "string"}, {"type": "null"}], "default": null, "title": "Name"}, "surname": {"anyOf": [{"type": "string"}, {"type": "null"}], "default": null, "title": "Surname"}, "birthdate": {"anyOf": [{"type": "string"}, {"type": "null"}], "default": null, "title": "Birthdate"}, "deceased": {"anyOf": [{"type": "boolean"}, {"type": "null"}], "default": null, "title": "Deceased"}, "addresses": {"items": {"$ref": "#/$defs/AddressDto"}, "title": "Addresses", "type": "array"}, "communications": {"items": {"$ref": "#/$defs/CommunicationDto"}, "title": "Communications", "type": "array"}}, "required": ["id", "resourceName", "ehrId"], "title": "PatientDto", "type": "object"}, "sample_payload": {"id": "232244334", "resourceType": "Patient", "resourceName": "Patient", "ehrId": "123456", "communications": [], "addresses": []}, "form_url": "http://localhost:8000/api/interfaces/patients/mock/operations/f77d6132-4300-44a5-a44b-c62255181ba5/form", "created_at": "2026-03-18T10:01:03.768280+00:00", "updated_at": "2026-03-18T10:01:52.902973+00:00"}, "9656f5b8-880d-4485-8457-4b8db190ce97": {"status": "ready", "operation_type": "patient", "payload": {"id": "433663563565", "resourceType": "Patient", "resourceName": "Patient", "ehrId": "123456", "communications": [{"communicationType": "PHONE", "use": "PRIVATE", "value": "0791234567"}], "addresses": [], "ahvNumber": null, "gender": "male", "name": "Ulli", "surname": "Schnulli", "birthdate": "01.01.1970", "deceased": null}, "status_code": null, "error_code": null, "error_detail": null, "schema": {"$defs": {"AddressDto": {"properties": {"country": {"anyOf": [{"type": "string"}, {"type": "null"}], "default": null, "title": "Country"}, "city": {"anyOf": [{"type": "string"}, {"type": "null"}], "default": null, "title": "City"}, "state": {"anyOf": [{"type": "string"}, {"type": "null"}], "default": null, "title": "State"}, "postalCode": {"anyOf": [{"type": "string"}, {"type": "null"}], "default": null, "title": "Postalcode"}, "street": {"anyOf": [{"type": "string"}, {"type": "null"}], "default": null, "title": "Street"}, "addressSupplement": {"anyOf": [{"type": "string"}, {"type": "null"}], "default": null, "title": "Addresssupplement"}}, "title": "AddressDto", "type": "object"}, "CommunicationDto": {"properties": {"communicationType": {"title": "Communicationtype", "type": "string", "enum": ["PHONE", "EMAIL", "FAX", "PAGER", "URL", "SMS"]}, "use": {"title": "Use", "type": "string", "enum": ["WORK", "PRIVATE", "HOME", "TEMP", "OLD", "HOLIDAY", "MOBILE", "OTHER"]}, "value": {"title": "Value", "type": "string"}}, "required": ["communicationType", "use", "value"], "title": "CommunicationDto", "type": "object"}}, "properties": {"id": {"title": "Id", "type": "string"}, "resourceType": {"default": "Patient", "title": "Resourcetype", "type": "string"}, "resourceName": {"title": "Resourcename", "type": "string"}, "ehrId": {"title": "Ehrid", "type": "string"}, "ahvNumber": {"anyOf": [{"type": "string"}, {"type": "null"}], "default": null, "title": "Ahvnumber"}, "gender": {"anyOf": [{"type": "string"}, {"type": "null"}], "default": null, "title": "Gender", "enum": ["male", "female", "diverse", "other", "unknown"]}, "name": {"anyOf": [{"type": "string"}, {"type": "null"}], "default": null, "title": "Name"}, "surname": {"anyOf": [{"type": "string"}, {"type": "null"}], "default": null, "title": "Surname"}, "birthdate": {"anyOf": [{"type": "string"}, {"type": "null"}], "default": null, "title": "Birthdate"}, "deceased": {"anyOf": [{"type": "boolean"}, {"type": "null"}], "default": null, "title": "Deceased"}, "addresses": {"items": {"$ref": "#/$defs/AddressDto"}, "title": "Addresses", "type": "array"}, "communications": {"items": {"$ref": "#/$defs/CommunicationDto"}, "title": "Communications", "type": "array"}}, "required": ["id", "resourceName", "ehrId"], "title": "PatientDto", "type": "object"}, "sample_payload": {"id": "433663563565", "resourceType": "Patient", "resourceName": "Patient", "ehrId": "123456", "communications": [], "addresses": []}, "form_url": "http://localhost:8000/api/interfaces/patients/mock/operations/9656f5b8-880d-4485-8457-4b8db190ce97/form", "created_at": "2026-03-26T10:31:11.203581+00:00", "updated_at": "2026-03-26T10:32:33.521197+00:00"}, "2e1dcd2f-39b6-4201-987a-108eb04a44b9": {"status": "ready", "operation_type": "patient", "payload": {"id": "356536536", "resourceType": "Patient", "resourceName": "Patient", "ehrId": "123456", "communications": [{"communicationType": "PHONE", "use": "PRIVATE", "value": "6363653635"}], "addresses": [], "ahvNumber": null, "gender": "female", "name": "Ulla", "surname": "Uhlmann", "birthdate": "01.01.1980", "deceased": null}, "status_code": null, "error_code": null, "error_detail": null, "schema": {"$defs": {"AddressDto": {"properties": {"country": {"anyOf": [{"type": "string"}, {"type": "null"}], "default": null, "title": "Country"}, "city": {"anyOf": [{"type": "string"}, {"type": "null"}], "default": null, "title": "City"}, "state": {"anyOf": [{"type": "string"}, {"type": "null"}], "default": null, "title": "State"}, "postalCode": {"anyOf": [{"type": "string"}, {"type": "null"}], "default": null, "title": "Postalcode"}, "street": {"anyOf": [{"type": "string"}, {"type": "null"}], "default": null, "title": "Street"}, "addressSupplement": {"anyOf": [{"type": "string"}, {"type": "null"}], "default": null, "title": "Addresssupplement"}}, "title": "AddressDto", "type": "object"}, "CommunicationDto": {"properties": {"communicationType": {"title": "Communicationtype", "type": "string", "enum": ["PHONE", "EMAIL", "FAX", "PAGER", "URL", "SMS"]}, "use": {"title": "Use", "type": "string", "enum": ["WORK", "PRIVATE", "HOME", "TEMP", "OLD", "HOLIDAY", "MOBILE", "OTHER"]}, "value": {"title": "Value", "type": "string"}}, "required": ["communicationType", "use", "value"], "title": "CommunicationDto", "type": "object"}}, "properties": {"id": {"title": "Id", "type": "string"}, "resourceType": {"default": "Patient", "title": "Resourcetype", "type": "string"}, "resourceName": {"title": "Resourcename", "type": "string"}, "ehrId": {"title": "Ehrid", "type": "string"}, "ahvNumber": {"anyOf": [{"type": "string"}, {"type": "null"}], "default": null, "title": "Ahvnumber"}, "gender": {"anyOf": [{"type": "string"}, {"type": "null"}], "default": null, "title": "Gender", "enum": ["male", "female", "diverse", "other", "unknown"]}, "name": {"anyOf": [{"type": "string"}, {"type": "null"}], "default": null, "title": "Name"}, "surname": {"anyOf": [{"type": "string"}, {"type": "null"}], "default": null, "title": "Surname"}, "birthdate": {"anyOf": [{"type": "string"}, {"type": "null"}], "default": null, "title": "Birthdate"}, "deceased": {"anyOf": [{"type": "boolean"}, {"type": "null"}], "default": null, "title": "Deceased"}, "addresses": {"items": {"$ref": "#/$defs/AddressDto"}, "title": "Addresses", "type": "array"}, "communications": {"items": {"$ref": "#/$defs/CommunicationDto"}, "title": "Communications", "type": "array"}}, "required": ["id", "resourceName", "ehrId"], "title": "PatientDto", "type": "object"}, "sample_payload": {"id": "356536536", "resourceType": "Patient", "resourceName": "Patient", "ehrId": "123456", "communications": [], "addresses": []}, "form_url": "http://localhost:8000/api/interfaces/patients/mock/operations/2e1dcd2f-39b6-4201-987a-108eb04a44b9/form", "created_at": "2026-03-26T11:42:01.525916+00:00", "updated_at": "2026-03-26T11:42:49.724045+00:00"}, "0c58475a-bb79-42a3-b795-1978caed5c96": {"status": "pending", "operation_type": "patient", "payload": null, "status_code": null, "error_code": null, "error_detail": null, "schema": {"$defs": {"AddressDto": {"properties": {"country": {"anyOf": [{"type": "string"}, {"type": "null"}], "default": null, "title": "Country"}, "city": {"anyOf": [{"type": "string"}, {"type": "null"}], "default": null, "title": "City"}, "state": {"anyOf": [{"type": "string"}, {"type": "null"}], "default": null, "title": "State"}, "postalCode": {"anyOf": [{"type": "string"}, {"type": "null"}], "default": null, "title": "Postalcode"}, "street": {"anyOf": [{"type": "string"}, {"type": "null"}], "default": null, "title": "Street"}, "addressSupplement": {"anyOf": [{"type": "string"}, {"type": "null"}], "default": null, "title": "Addresssupplement"}}, "title": "AddressDto", "type": "object"}, "CommunicationDto": {"properties": {"communicationType": {"title": "Communicationtype", "type": "string", "enum": ["PHONE", "EMAIL", "FAX", "PAGER", "URL", "SMS"]}, "use": {"title": "Use", "type": "string", "enum": ["WORK", "PRIVATE", "HOME", "TEMP", "OLD", "HOLIDAY", "MOBILE", "OTHER"]}, "value": {"title": "Value", "type": "string"}}, "required": ["communicationType", "use", "value"], "title": "CommunicationDto", "type": "object"}}, "properties": {"id": {"title": "Id", "type": "string"}, "resourceType": {"default": "Patient", "title": "Resourcetype", "type": "string"}, "resourceName": {"title": "Resourcename", "type": "string"}, "ehrId": {"title": "Ehrid", "type": "string"}, "ahvNumber": {"anyOf": [{"type": "string"}, {"type": "null"}], "default": null, "title": "Ahvnumber"}, "gender": {"anyOf": [{"type": "string"}, {"type": "null"}], "default": null, "title": "Gender", "enum": ["male", "female", "diverse", "other", "unknown"]}, "name": {"anyOf": [{"type": "string"}, {"type": "null"}], "default": null, "title": "Name"}, "surname": {"anyOf": [{"type": "string"}, {"type": "null"}], "default": null, "title": "Surname"}, "birthdate": {"anyOf": [{"type": "string"}, {"type": "null"}], "default": null, "title": "Birthdate"}, "deceased": {"anyOf": [{"type": "boolean"}, {"type": "null"}], "default": null, "title": "Deceased"}, "addresses": {"items": {"$ref": "#/$defs/AddressDto"}, "title": "Addresses", "type": "array"}, "communications": {"items": {"$ref": "#/$defs/CommunicationDto"}, "title": "Communications", "type": "array"}}, "required": ["id", "resourceName", "ehrId"], "title": "PatientDto", "type": "object"}, "sample_payload": {"id": "6456454545", "resourceType": "Patient", "resourceName": "Patient", "ehrId": "123456", "communications": [], "addresses": []}, "form_url": "http://localhost:8000/api/interfaces/patients/mock/operations/0c58475a-bb79-42a3-b795-1978caed5c96/form", "created_at": "2026-03-26T11:50:39.933378+00:00", "updated_at": "2026-03-26T11:50:39.933414+00:00"}}, "op_id_by_key": {"patient|7411||": "b2f63c2c-9c5f-43f1-9e92-49f7d9f19a41", "patient|4711343||": "0378e267-8e2a-439a-b7af-649a35a5e710", "patient|545345346246||": "2a43da0b-c513-406f-a616-da7c9850c297", "patient|232244334||": "f77d6132-4300-44a5-a44b-c62255181ba5", "patient|433663563565||": "9656f5b8-880d-4485-8457-4b8db190ce97", "patient|356536536||": "2e1dcd2f-39b6-4201-987a-108eb04a44b9", "patient|6456454545||": "0c58475a-bb79-42a3-b795-1978caed5c96"}}